ovos_skill_tunein/LICENSE
ovos_skill_tunein/MANIFEST.in
ovos_skill_tunein/README.md
ovos_skill_tunein/__init__.py
ovos_skill_tunein/requirements.txt
ovos_skill_tunein/version.py
ovos_skill_tunein/locale/ca-es/radio.voc
ovos_skill_tunein/locale/ca-es/tunein.voc
ovos_skill_tunein/locale/cs-cz/radio.voc
ovos_skill_tunein/locale/cs-cz/tunein.voc
ovos_skill_tunein/locale/da-dk/radio.voc
ovos_skill_tunein/locale/da-dk/tunein.voc
ovos_skill_tunein/locale/de-de/radio.voc
ovos_skill_tunein/locale/de-de/tunein.voc
ovos_skill_tunein/locale/en-us/radio.voc
ovos_skill_tunein/locale/en-us/skill.json
ovos_skill_tunein/locale/en-us/tunein.voc
ovos_skill_tunein/locale/en-us/tunein_skill.voc
ovos_skill_tunein/locale/es-es/radio.voc
ovos_skill_tunein/locale/es-es/tunein.voc
ovos_skill_tunein/locale/fr-fr/radio.voc
ovos_skill_tunein/locale/fr-fr/tunein.voc
ovos_skill_tunein/locale/hu-hu/radio.voc
ovos_skill_tunein/locale/hu-hu/tunein.voc
ovos_skill_tunein/locale/it-it/radio.voc
ovos_skill_tunein/locale/it-it/tunein.voc
ovos_skill_tunein/locale/nl-nl/radio.voc
ovos_skill_tunein/locale/nl-nl/tunein.voc
ovos_skill_tunein/locale/pl-pl/radio.voc
ovos_skill_tunein/locale/pl-pl/tunein.voc
ovos_skill_tunein/locale/pt-pt/radio.voc
ovos_skill_tunein/locale/pt-pt/tunein.voc
ovos_skill_tunein/locale/ru-ru/radio.voc
ovos_skill_tunein/locale/ru-ru/tunein.voc
ovos_skill_tunein/locale/sv-fi/radio.voc
ovos_skill_tunein/locale/sv-fi/tunein.voc
ovos_skill_tunein/locale/sv-se/radio.voc
ovos_skill_tunein/locale/sv-se/tunein.voc
ovos_skill_tunein/ovos_skill_tunein.egg-info/PKG-INFO
ovos_skill_tunein/ovos_skill_tunein.egg-info/SOURCES.txt
ovos_skill_tunein/ovos_skill_tunein.egg-info/dependency_links.txt
ovos_skill_tunein/ovos_skill_tunein.egg-info/entry_points.txt
ovos_skill_tunein/ovos_skill_tunein.egg-info/requires.txt
ovos_skill_tunein/ovos_skill_tunein.egg-info/top_level.txt
ovos_skill_tunein-0.0.5.dist-info/LICENSE
ovos_skill_tunein-0.0.5.dist-info/METADATA
ovos_skill_tunein-0.0.5.dist-info/WHEEL
ovos_skill_tunein-0.0.5.dist-info/entry_points.txt
ovos_skill_tunein-0.0.5.dist-info/top_level.txt
ovos_skill_tunein-0.0.5.dist-info/RECORD
