Metadata-Version: 2.1
Name: ovos-skill-tunein
Version: 0.0.5
Summary: ovos tunein skill plugin
Home-page: https://github.com/OpenVoiceOS/skill-ovos-tunein
Author: JarbasAi
Author-email: jarbasai@mailfence.com
License: Apache-2.0
Keywords: ovos skill plugin
Platform: UNKNOWN
Requires-Dist: ovos-utils>=0.1.0
Requires-Dist: ovos-bus-client>=0.0.9
Requires-Dist: ovos-workshop>=0.0.16
Requires-Dist: tunein>=0.0.4a1,~=0.0
